django_rest_structure/__init__.py
django_rest_structure/apps.py
django_rest_structure/configs.py
django_rest_structure/api/__init__.py
django_rest_structure/api/serializers.py
django_rest_structure/api/validations.py
django_rest_structure/api/views.py
django_rest_structure/logs/__init__.py
django_rest_structure/logs/console.py
django_rest_structure/middlewares/__init__.py
django_rest_structure/middlewares/middleware.py
django_rest_structure/migrations/__init__.py
django_rest_structure/requests/__init__.py
django_rest_structure/requests/tools.py
django_rest_structure/results/__init__.py
django_rest_structure/results/codes.py
django_rest_structure/results/exception.py
django_rest_structure/results/response.py
django_rest_structure/results/structure.py
django_rest_structure/translations/__init__.py
django_rest_structure/translations/translate.py
django_rest_structure/translations/locales/en-us.json
django_rest_structure/translations/locales/fa-ir.json
django_rest_structure-1.1.5.data/data/locales/en-us.json
django_rest_structure-1.1.5.data/data/locales/fa-ir.json
django_rest_structure-1.1.5.dist-info/LICENSE
django_rest_structure-1.1.5.dist-info/METADATA
django_rest_structure-1.1.5.dist-info/WHEEL
django_rest_structure-1.1.5.dist-info/top_level.txt
django_rest_structure-1.1.5.dist-info/RECORD
