Metadata-Version: 2.1
Name: django-rest-structure
Version: 1.1.5
Summary: Structure for django rest framework.
Home-page: https://github.com/ArefMousakhani/django_rest_structure
Author: Aref Mousakhani
Author-email: aref.mousakhani@gmail.com
Requires-Python: >=3.8
License-File: LICENSE
Requires-Dist: djangorestframework (>=3.12.4)
Requires-Dist: django (>=3.0.0)
